square/__init__.py
square/__main__.py
squaretheinput-1.0.0.dist-info/LICENSE
squaretheinput-1.0.0.dist-info/METADATA
squaretheinput-1.0.0.dist-info/WHEEL
squaretheinput-1.0.0.dist-info/entry_points.txt
squaretheinput-1.0.0.dist-info/top_level.txt
squaretheinput-1.0.0.dist-info/RECORD
